gitlab_webhook_receiver/__init__.py
gitlab_webhook_receiver/receiver.py
gitlab_webhook_receiver-0.1.0.dist-info/METADATA
gitlab_webhook_receiver-0.1.0.dist-info/WHEEL
gitlab_webhook_receiver-0.1.0.dist-info/entry_points.txt
gitlab_webhook_receiver-0.1.0.dist-info/top_level.txt
gitlab_webhook_receiver-0.1.0.dist-info/RECORD
